badgegen/__init__.py
badgegen-0.2.data/scripts/badgegen
badgegen-0.2.dist-info/METADATA
badgegen-0.2.dist-info/WHEEL
badgegen-0.2.dist-info/top_level.txt
badgegen-0.2.dist-info/RECORD
