Metadata-Version: 2.1
Name: badgegen
Version: 0.2
Summary: CI/CD Badge Generator
Home-page: https://github.com/alexhagen/badgegen
Author: Alex Hagen
Author-email: alexhagen6@gmail.com
License: UNKNOWN
Platform: UNKNOWN
Requires-Dist: svgwrite
